CONTRIBUTING.md
LICENSE
MANIFEST.in
README.md
setup.cfg
setup.py
keras_preprocessing/__init__.py
keras_preprocessing/sequence.py
keras_preprocessing/text.py
keras_preprocessing/image/__init__.py
keras_preprocessing/image/affine_transformations.py
keras_preprocessing/image/dataframe_iterator.py
keras_preprocessing/image/directory_iterator.py
keras_preprocessing/image/image_data_generator.py
keras_preprocessing/image/iterator.py
keras_preprocessing/image/numpy_array_iterator.py
keras_preprocessing/image/utils.py
tests/sequence_test.py
tests/test_api.py
tests/test_documentation.py
tests/text_test.py
tests/image/affine_transformations_test.py
tests/image/dataframe_iterator_test.py
tests/image/directory_iterator_test.py
tests/image/image_data_generator_test.py
tests/image/iterator_test.py
tests/image/numpy_array_iterator_test.py
tests/image/test_image_api.py
tests/image/utils_test.py
yale_dhlab_keras_preprocessing.egg-info/PKG-INFO
yale_dhlab_keras_preprocessing.egg-info/SOURCES.txt
yale_dhlab_keras_preprocessing.egg-info/dependency_links.txt
yale_dhlab_keras_preprocessing.egg-info/requires.txt
yale_dhlab_keras_preprocessing.egg-info/top_level.txt